cpptypes/__init__.py
cpptypes/__main__.py
cpptypes/create_cpp_bindings.py
cpptypes/create_py_bindings.py
cpptypes/parse_cpp_exports.py
cpptypes-0.1.0.dist-info/METADATA
cpptypes-0.1.0.dist-info/WHEEL
cpptypes-0.1.0.dist-info/entry_points.txt
cpptypes-0.1.0.dist-info/top_level.txt
cpptypes-0.1.0.dist-info/RECORD
