Metadata-Version: 2.1
Name: cpptypes
Version: 0.1.0
Summary: Automatically creates the C++ and Python-side wrappers for ctypes bindings.
Home-page: https://github.com/biocpy/cpptypes
Author: Aaron Lun
Author-email: infinite.monkeys.with.keyboards@gmail.com
License: MIT
Project-URL: Documentation, https://github.com/biocpy/cpptypes
Platform: any
Classifier: Development Status :: 4 - Beta
Classifier: Programming Language :: Python
Requires-Dist: importlib-metadata ; python_version < "3.8"
Provides-Extra: testing
Requires-Dist: setuptools ; extra == 'testing'
Requires-Dist: pytest ; extra == 'testing'
Requires-Dist: pytest-cov ; extra == 'testing'
